{
  "legislative_session": "2025-2026",
  "identifier": "HB 5536",
  "title": "Natural resources: wetlands; definition of wetland; update. Amends secs. 30301, 30307 & 30308 of 1994 PA 451 (MCL 324.30301 et seq.).",
  "from_organization": "~{\"classification\": \"lower\"}",
  "classification": [
    "bill"
  ],
  "subject": [
    "Natural resources: wetlands",
    "State agencies (existing): environment, Great Lakes, and energy"
  ],
  "abstracts": [],
  "other_titles": [],
  "other_identifiers": [
    {
      "identifier": "ocd-bill-mi-2025_2026-hb5536"
    }
  ],
  "actions": [
    {
      "description": "introduced by Representative Rep. David Martin",
      "date": "2026-02-19",
      "organization_id": "~{\"classification\": \"lower\"}",
      "classification": [
        "introduction"
      ],
      "related_entities": [],
      "_processing": {
        "log_file_created": "2026-07-14T13:50:47Z"
      }
    },
    {
      "description": "read a first time",
      "date": "2026-02-19",
      "organization_id": "~{\"classification\": \"lower\"}",
      "classification": [
        "reading-1"
      ],
      "related_entities": [],
      "_processing": {
        "log_file_created": "2026-07-14T13:50:47Z"
      }
    },
    {
      "description": "referred to Committee on Natural Resources and Tourism",
      "date": "2026-02-19",
      "organization_id": "~{\"classification\": \"lower\"}",
      "classification": [
        "referral-committee"
      ],
      "related_entities": [],
      "_processing": {
        "log_file_created": "2026-07-14T13:50:47Z"
      }
    },
    {
      "description": "bill electronically reproduced 02/19/2026",
      "date": "2026-02-24",
      "organization_id": "~{\"classification\": \"lower\"}",
      "classification": [],
      "related_entities": [],
      "_processing": {
        "log_file_created": "2026-07-14T13:50:47Z"
      }
    },
    {
      "description": "reported with recommendation for referral to Committee on Rules",
      "date": "2026-04-29",
      "organization_id": "~{\"classification\": \"lower\"}",
      "classification": [
        "committee-passage"
      ],
      "related_entities": [],
      "_processing": {
        "log_file_created": "2026-07-14T13:50:47Z"
      }
    },
    {
      "description": "recommendation concurred in",
      "date": "2026-04-29",
      "organization_id": "~{\"classification\": \"lower\"}",
      "classification": [],
      "related_entities": [],
      "_processing": {
        "log_file_created": "2026-07-14T13:50:47Z"
      }
    },
    {
      "description": "reported with recommendation without amendment",
      "date": "2026-05-21",
      "organization_id": "~{\"classification\": \"lower\"}",
      "classification": [
        "committee-passage"
      ],
      "related_entities": [],
      "_processing": {
        "log_file_created": "2026-07-14T13:50:47Z"
      }
    },
    {
      "description": "referred to second reading",
      "date": "2026-05-21",
      "organization_id": "~{\"classification\": \"lower\"}",
      "classification": [],
      "related_entities": [],
      "_processing": {
        "log_file_created": "2026-07-14T13:50:47Z"
      }
    },
    {
      "description": "read a second time",
      "date": "2026-06-03",
      "organization_id": "~{\"classification\": \"lower\"}",
      "classification": [
        "reading-2"
      ],
      "related_entities": [],
      "_processing": {
        "log_file_created": "2026-07-14T13:50:47Z"
      }
    },
    {
      "description": "placed on third reading",
      "date": "2026-06-03",
      "organization_id": "~{\"classification\": \"lower\"}",
      "classification": [],
      "related_entities": [],
      "_processing": {
        "log_file_created": "2026-07-14T13:50:47Z"
      }
    },
    {
      "description": "read a third time",
      "date": "2026-06-04",
      "organization_id": "~{\"classification\": \"lower\"}",
      "classification": [
        "reading-3"
      ],
      "related_entities": [],
      "_processing": {
        "log_file_created": "2026-07-14T13:50:47Z"
      }
    },
    {
      "description": "passed; given immediate effect Roll Call #182 Yeas 57 Nays 51 Excused 0 Not Voting 2",
      "date": "2026-06-04",
      "organization_id": "~{\"classification\": \"lower\"}",
      "classification": [
        "passage"
      ],
      "related_entities": [],
      "_processing": {
        "log_file_created": "2026-07-14T13:50:47Z"
      }
    },
    {
      "description": "transmitted",
      "date": "2026-06-04",
      "organization_id": "~{\"classification\": \"lower\"}",
      "classification": [],
      "related_entities": [],
      "_processing": {
        "log_file_created": "2026-07-14T13:50:47Z"
      }
    },
    {
      "description": "PASSED BY HOUSE WITH IMMEDIATE EFFECT",
      "date": "2026-06-10",
      "organization_id": "~{\"classification\": \"upper\"}",
      "classification": [
        "passage"
      ],
      "related_entities": [],
      "_processing": {
        "log_file_created": "2026-07-14T13:50:47Z"
      }
    },
    {
      "description": "REFERRED TO COMMITTEE ON NATURAL RESOURCES AND AGRICULTURE",
      "date": "2026-06-10",
      "organization_id": "~{\"classification\": \"upper\"}",
      "classification": [
        "referral-committee"
      ],
      "related_entities": [],
      "_processing": {
        "log_file_created": "2026-07-14T13:50:47Z"
      }
    }
  ],
  "sponsorships": [
    {
      "name": "David Martin",
      "classification": "primary",
      "entity_type": "person",
      "primary": true,
      "person_id": "~{\"name\": \"David Martin\"}",
      "organization_id": null
    },
    {
      "name": "Bill Schuette",
      "classification": "cosponsor",
      "entity_type": "person",
      "primary": false,
      "person_id": "~{\"name\": \"Bill Schuette\"}",
      "organization_id": null
    },
    {
      "name": "Jerry Neyer",
      "classification": "cosponsor",
      "entity_type": "person",
      "primary": false,
      "person_id": "~{\"name\": \"Jerry Neyer\"}",
      "organization_id": null
    },
    {
      "name": "Cameron Cavitt",
      "classification": "cosponsor",
      "entity_type": "person",
      "primary": false,
      "person_id": "~{\"name\": \"Cameron Cavitt\"}",
      "organization_id": null
    },
    {
      "name": "Tom Kunse",
      "classification": "cosponsor",
      "entity_type": "person",
      "primary": false,
      "person_id": "~{\"name\": \"Tom Kunse\"}",
      "organization_id": null
    },
    {
      "name": "Bradley Slagh",
      "classification": "cosponsor",
      "entity_type": "person",
      "primary": false,
      "person_id": "~{\"name\": \"Bradley Slagh\"}",
      "organization_id": null
    },
    {
      "name": "Karl Bohnak",
      "classification": "cosponsor",
      "entity_type": "person",
      "primary": false,
      "person_id": "~{\"name\": \"Karl Bohnak\"}",
      "organization_id": null
    },
    {
      "name": "Gregory Markkanen",
      "classification": "cosponsor",
      "entity_type": "person",
      "primary": false,
      "person_id": "~{\"name\": \"Gregory Markkanen\"}",
      "organization_id": null
    },
    {
      "name": "Ken Borton",
      "classification": "cosponsor",
      "entity_type": "person",
      "primary": false,
      "person_id": "~{\"name\": \"Ken Borton\"}",
      "organization_id": null
    },
    {
      "name": "Josh Schriver",
      "classification": "cosponsor",
      "entity_type": "person",
      "primary": false,
      "person_id": "~{\"name\": \"Josh Schriver\"}",
      "organization_id": null
    },
    {
      "name": "Sarah Lightner",
      "classification": "cosponsor",
      "entity_type": "person",
      "primary": false,
      "person_id": "~{\"name\": \"Sarah Lightner\"}",
      "organization_id": null
    },
    {
      "name": "Gregory Alexander",
      "classification": "cosponsor",
      "entity_type": "person",
      "primary": false,
      "person_id": "~{\"name\": \"Gregory Alexander\"}",
      "organization_id": null
    },
    {
      "name": "Alicia St. Germaine",
      "classification": "cosponsor",
      "entity_type": "person",
      "primary": false,
      "person_id": "~{\"name\": \"Alicia St. Germaine\"}",
      "organization_id": null
    },
    {
      "name": "John Roth",
      "classification": "cosponsor",
      "entity_type": "person",
      "primary": false,
      "person_id": "~{\"name\": \"John Roth\"}",
      "organization_id": null
    },
    {
      "name": "Tim Kelly",
      "classification": "cosponsor",
      "entity_type": "person",
      "primary": false,
      "person_id": "~{\"name\": \"Tim Kelly\"}",
      "organization_id": null
    },
    {
      "name": "Steve Frisbie",
      "classification": "cosponsor",
      "entity_type": "person",
      "primary": false,
      "person_id": "~{\"name\": \"Steve Frisbie\"}",
      "organization_id": null
    },
    {
      "name": "Jennifer Wortz",
      "classification": "cosponsor",
      "entity_type": "person",
      "primary": false,
      "person_id": "~{\"name\": \"Jennifer Wortz\"}",
      "organization_id": null
    }
  ],
  "related_bills": [],
  "versions": [
    {
      "note": "House Introduced Bill",
      "links": [
        {
          "url": "https://legislature.mi.gov/documents/2025-2026/billintroduced/House/pdf/2026-HIB-5536.pdf",
          "media_type": "application/pdf"
        },
        {
          "url": "https://legislature.mi.gov/documents/2025-2026/billintroduced/House/htm/2026-HIB-5536.htm",
          "media_type": "text/html"
        }
      ],
      "date": "",
      "classification": ""
    },
    {
      "note": "As Passed by the House",
      "links": [
        {
          "url": "https://legislature.mi.gov/documents/2025-2026/billengrossed/House/pdf/2026-HEBH-5536.pdf",
          "media_type": "application/pdf"
        },
        {
          "url": "https://legislature.mi.gov/documents/2025-2026/billengrossed/House/htm/2026-HEBH-5536.htm",
          "media_type": "text/html"
        }
      ],
      "date": "",
      "classification": ""
    }
  ],
  "documents": [
    {
      "note": "Revised Summary as Introduced (5/5/2026)",
      "links": [
        {
          "url": "https://legislature.mi.gov/documents/2025-2026/billanalysis/House/pdf/2026-HLA-5536-0DFLVT68.pdf",
          "media_type": "application/pdf"
        }
      ],
      "date": "",
      "classification": ""
    },
    {
      "note": "Summary as Reported from Committee (6/4/2026)",
      "links": [
        {
          "url": "https://legislature.mi.gov/documents/2025-2026/billanalysis/House/pdf/2026-HLA-5536-9RP78QVH.pdf",
          "media_type": "application/pdf"
        }
      ],
      "date": "",
      "classification": ""
    }
  ],
  "citations": [
    {
      "publication": "Michigan Compiled Laws",
      "citation": "MCL 324.30301",
      "citation_type": "proposed",
      "effective": null,
      "expires": null,
      "url": null
    }
  ],
  "sources": [
    {
      "url": "https://legislature.mi.gov/Bills/Bill?ObjectName=2026-HB-5536",
      "note": ""
    }
  ],
  "extras": {},
  "jurisdiction": {
    "id": "ocd-jurisdiction/country:us/state:mi/government",
    "name": "Michigan",
    "classification": "state",
    "division_id": "ocd-division/country:us/state:mi"
  },
  "_processing": {
    "logs_latest_update": "2026-07-14T13:50:47Z",
    "text_extraction_latest_update": "2026-07-14T22:14:32.642910Z"
  }
}