{
  "legislative_session": "2025-2026",
  "identifier": "HB 5720",
  "title": "Highways: memorial; portion of M-5; designate as the \"Joseph R. Blake Memorial Highway\". Amends 2001 PA 142 (MCL 250.1001 - 250.2092) by adding sec. 122.",
  "from_organization": "~{\"classification\": \"lower\"}",
  "classification": [
    "bill"
  ],
  "subject": [
    "Highways: memorial",
    "State agencies (existing): transportation"
  ],
  "abstracts": [],
  "other_titles": [],
  "other_identifiers": [
    {
      "identifier": "ocd-bill-mi-2025_2026-hb5720"
    }
  ],
  "actions": [
    {
      "description": "introduced by Representative Rep. Laurie Pohutsky",
      "date": "2026-03-17",
      "organization_id": "~{\"classification\": \"lower\"}",
      "classification": [
        "introduction"
      ],
      "related_entities": [],
      "_processing": {
        "log_file_created": "2026-07-14T13:50:47Z"
      }
    },
    {
      "description": "read a first time",
      "date": "2026-03-17",
      "organization_id": "~{\"classification\": \"lower\"}",
      "classification": [
        "reading-1"
      ],
      "related_entities": [],
      "_processing": {
        "log_file_created": "2026-07-14T13:50:47Z"
      }
    },
    {
      "description": "referred to Committee on Transportation and Infrastructure",
      "date": "2026-03-17",
      "organization_id": "~{\"classification\": \"lower\"}",
      "classification": [
        "referral-committee"
      ],
      "related_entities": [],
      "_processing": {
        "log_file_created": "2026-07-14T13:50:47Z"
      }
    },
    {
      "description": "bill electronically reproduced 03/17/2026",
      "date": "2026-03-18",
      "organization_id": "~{\"classification\": \"lower\"}",
      "classification": [],
      "related_entities": [],
      "_processing": {
        "log_file_created": "2026-07-14T13:50:47Z"
      }
    }
  ],
  "sponsorships": [
    {
      "name": "Laurie Pohutsky",
      "classification": "primary",
      "entity_type": "person",
      "primary": true,
      "person_id": "~{\"name\": \"Laurie Pohutsky\"}",
      "organization_id": null
    }
  ],
  "related_bills": [],
  "versions": [
    {
      "note": "House Introduced Bill",
      "links": [
        {
          "url": "https://legislature.mi.gov/documents/2025-2026/billintroduced/House/pdf/2026-HIB-5720.pdf",
          "media_type": "application/pdf"
        },
        {
          "url": "https://legislature.mi.gov/documents/2025-2026/billintroduced/House/htm/2026-HIB-5720.htm",
          "media_type": "text/html"
        }
      ],
      "date": "",
      "classification": ""
    }
  ],
  "documents": [],
  "citations": [
    {
      "publication": "Michigan Compiled Laws",
      "citation": "MCL 250.1001",
      "citation_type": "proposed",
      "effective": null,
      "expires": null,
      "url": null
    },
    {
      "publication": "Michigan Compiled Laws",
      "citation": "MCL 250.2092",
      "citation_type": "proposed",
      "effective": null,
      "expires": null,
      "url": null
    }
  ],
  "sources": [
    {
      "url": "https://legislature.mi.gov/Bills/Bill?ObjectName=2026-HB-5720",
      "note": ""
    }
  ],
  "extras": {},
  "jurisdiction": {
    "id": "ocd-jurisdiction/country:us/state:mi/government",
    "name": "Michigan",
    "classification": "state",
    "division_id": "ocd-division/country:us/state:mi"
  },
  "_processing": {
    "logs_latest_update": "2026-07-14T13:50:47Z",
    "text_extraction_latest_update": "2026-07-14T21:31:31.874728Z"
  }
}