{
  "identifier": "",
  "motion_text": "PASSED; GIVEN IMMEDIATE EFFECT ROLL CALL # 178 YEAS 26 NAYS 10 EXCUSED 2 NOT VOTING 0",
  "motion_classification": [
    "passage"
  ],
  "start_date": "2026-07-03",
  "result": "fail",
  "organization": "~{\"classification\": \"upper\"}",
  "legislative_session": "2025-2026",
  "bill": "22557ec2-7f48-11f1-82e4-eab9223700e3",
  "bill_action": null,
  "bill_identifier": "HB 4471",
  "votes": [
    {
      "option": "no",
      "voter_name": "Albert",
      "voter_id": "~{\"name\": \"Albert\"}",
      "note": ""
    },
    {
      "option": "no",
      "voter_name": "Daley Hauck",
      "voter_id": "~{\"name\": \"Daley Hauck\"}",
      "note": ""
    },
    {
      "option": "no",
      "voter_name": "Hoitenga",
      "voter_id": "~{\"name\": \"Hoitenga\"}",
      "note": ""
    },
    {
      "option": "no",
      "voter_name": "Irwin Johnson",
      "voter_id": "~{\"name\": \"Irwin Johnson\"}",
      "note": ""
    },
    {
      "option": "no",
      "voter_name": "Lindsey McBroom",
      "voter_id": "~{\"name\": \"Lindsey McBroom\"}",
      "note": ""
    },
    {
      "option": "no",
      "voter_name": "Nesbitt Runestad",
      "voter_id": "~{\"name\": \"Nesbitt Runestad\"}",
      "note": ""
    },
    {
      "option": "no",
      "voter_name": "Lauwers",
      "voter_id": "~{\"name\": \"Lauwers\"}",
      "note": ""
    },
    {
      "option": "no",
      "voter_name": "Santana",
      "voter_id": "~{\"name\": \"Santana\"}",
      "note": ""
    }
  ],
  "counts": [
    {
      "option": "yes",
      "value": 4
    },
    {
      "option": "no",
      "value": 8
    },
    {
      "option": "other",
      "value": 0
    }
  ],
  "sources": [
    {
      "url": "https://legislature.mi.gov/documents/2025-2026/Journal/Senate/htm/2026-SJ-07-03-062.htm",
      "note": ""
    }
  ],
  "extras": {}
}