{
  "action": {
    "description": "passed; given immediate effect Roll Call #334 Yeas 103 Nays 3 Excused 0 Not Voting 4",
    "occurred_at": "2025-12-16",
    "jurisdiction_id": "~{\"classification\": \"lower\"}",
    "session_id": "2025-2026",
    "entity_type": "bill",
    "classifications": [
      "passage"
    ],
    "related_entities": [],
    "sources": [
      {
        "url": "https://legislature.mi.gov/Bills/Bill?ObjectName=2025-SB-0699",
        "note": ""
      }
    ]
  },
  "bill_id": "SB 0699"
}