{
  "legislative_session": "2025-2026",
  "identifier": "SB 0988",
  "title": "Property tax: tax tribunal; number of days to appeal a claim for poverty exemption; modify. Amends sec. 53c of 1893 PA 206 (MCL 211.53c).",
  "from_organization": "~{\"classification\": \"upper\"}",
  "classification": [
    "bill"
  ],
  "subject": [
    "Property tax: tax tribunal"
  ],
  "abstracts": [],
  "other_titles": [],
  "other_identifiers": [
    {
      "identifier": "ocd-bill-mi-2025_2026-sb988"
    }
  ],
  "actions": [
    {
      "description": "INTRODUCED BY SENATOR SYLVIA SANTANA",
      "date": "2026-05-20",
      "organization_id": "~{\"classification\": \"upper\"}",
      "classification": [
        "introduction"
      ],
      "related_entities": [],
      "_processing": {
        "log_file_created": "2026-07-14T13:50:48Z"
      }
    },
    {
      "description": "REFERRED TO COMMITTEE ON FINANCE, INSURANCE, AND CONSUMER PROTECTION",
      "date": "2026-05-20",
      "organization_id": "~{\"classification\": \"upper\"}",
      "classification": [
        "referral-committee"
      ],
      "related_entities": [],
      "_processing": {
        "log_file_created": "2026-07-14T13:50:48Z"
      }
    },
    {
      "description": "REPORTED FAVORABLY WITHOUT AMENDMENT 6/23/2026",
      "date": "2026-06-24",
      "organization_id": "~{\"classification\": \"upper\"}",
      "classification": [
        "committee-passage"
      ],
      "related_entities": [],
      "_processing": {
        "log_file_created": "2026-07-14T13:50:48Z"
      }
    },
    {
      "description": "REFERRED TO COMMITTEE OF THE WHOLE",
      "date": "2026-06-24",
      "organization_id": "~{\"classification\": \"upper\"}",
      "classification": [
        "referral-committee"
      ],
      "related_entities": [],
      "_processing": {
        "log_file_created": "2026-07-14T13:50:48Z"
      }
    }
  ],
  "sponsorships": [
    {
      "name": "Sylvia A. Santana",
      "classification": "primary",
      "entity_type": "person",
      "primary": true,
      "person_id": "~{\"name\": \"Sylvia A. Santana\"}",
      "organization_id": null
    }
  ],
  "related_bills": [],
  "versions": [
    {
      "note": "Senate Introduced Bill",
      "links": [
        {
          "url": "https://legislature.mi.gov/documents/2025-2026/billintroduced/Senate/pdf/2026-SIB-0988.pdf",
          "media_type": "application/pdf"
        },
        {
          "url": "https://legislature.mi.gov/documents/2025-2026/billintroduced/Senate/htm/2026-SIB-0988.htm",
          "media_type": "text/html"
        }
      ],
      "date": "",
      "classification": ""
    }
  ],
  "documents": [
    {
      "note": "SUMMARY OF INTRODUCED BILL IN COMMITTEE (Date Completed: 6-22-26)",
      "links": [
        {
          "url": "https://legislature.mi.gov/documents/2025-2026/billanalysis/Senate/pdf/2026-SFA-0988-G.pdf",
          "media_type": "application/pdf"
        },
        {
          "url": "https://legislature.mi.gov/documents/2025-2026/billanalysis/Senate/htm/2026-SFA-0988-G.htm",
          "media_type": "text/html"
        }
      ],
      "date": "",
      "classification": ""
    },
    {
      "note": "SUMMARY OF BILL REPORTED FROM COMMITTEE (Date Completed: 6-26-26)",
      "links": [
        {
          "url": "https://legislature.mi.gov/documents/2025-2026/billanalysis/Senate/pdf/2026-SFA-0988-F.pdf",
          "media_type": "application/pdf"
        },
        {
          "url": "https://legislature.mi.gov/documents/2025-2026/billanalysis/Senate/htm/2026-SFA-0988-F.htm",
          "media_type": "text/html"
        }
      ],
      "date": "",
      "classification": ""
    }
  ],
  "citations": [
    {
      "publication": "Michigan Compiled Laws",
      "citation": "MCL 211.53c",
      "citation_type": "proposed",
      "effective": null,
      "expires": null,
      "url": null
    }
  ],
  "sources": [
    {
      "url": "https://legislature.mi.gov/Bills/Bill?ObjectName=2026-SB-0988",
      "note": ""
    }
  ],
  "extras": {},
  "jurisdiction": {
    "id": "ocd-jurisdiction/country:us/state:mi/government",
    "name": "Michigan",
    "classification": "state",
    "division_id": "ocd-division/country:us/state:mi"
  },
  "_processing": {
    "logs_latest_update": "2026-07-14T13:50:48Z"
  }
}