{
  "legislative_session": "2025-2026",
  "identifier": "HB 5313",
  "title": "Health: licensing; setting aside certain disciplinary records; provide for, and modify certain continuing education requirements and sanctions. Amends secs. 16211, 16216, 16221, 16226, 16231, 16238, 17033 & 17533 of 1978 PA 368  (MCL 333.16211 et seq.) & adds secs. 16211a & 16231b.",
  "from_organization": "~{\"classification\": \"lower\"}",
  "classification": [
    "bill"
  ],
  "subject": [
    "Health: licensing",
    "Health: occupations",
    "State agencies (existing): licensing and regulatory affairs"
  ],
  "abstracts": [],
  "other_titles": [],
  "other_identifiers": [
    {
      "identifier": "ocd-bill-mi-2025_2026-hb5313"
    }
  ],
  "actions": [
    {
      "description": "introduced by Representative Rep. Matthew Bierlein",
      "date": "2025-12-02",
      "organization_id": "~{\"classification\": \"lower\"}",
      "classification": [
        "introduction"
      ],
      "related_entities": [],
      "_processing": {
        "log_file_created": "2026-07-14T13:50:46Z"
      }
    },
    {
      "description": "read a first time",
      "date": "2025-12-02",
      "organization_id": "~{\"classification\": \"lower\"}",
      "classification": [
        "reading-1"
      ],
      "related_entities": [],
      "_processing": {
        "log_file_created": "2026-07-14T13:50:46Z"
      }
    },
    {
      "description": "referred to Committee on Health Policy",
      "date": "2025-12-02",
      "organization_id": "~{\"classification\": \"lower\"}",
      "classification": [
        "referral-committee"
      ],
      "related_entities": [],
      "_processing": {
        "log_file_created": "2026-07-14T13:50:46Z"
      }
    },
    {
      "description": "bill electronically reproduced 12/02/2025",
      "date": "2025-12-09",
      "organization_id": "~{\"classification\": \"lower\"}",
      "classification": [],
      "related_entities": [],
      "_processing": {
        "log_file_created": "2026-07-14T13:50:46Z"
      }
    },
    {
      "description": "reported with recommendation for referral to Committee on Rules",
      "date": "2026-02-18",
      "organization_id": "~{\"classification\": \"lower\"}",
      "classification": [
        "committee-passage"
      ],
      "related_entities": [],
      "_processing": {
        "log_file_created": "2026-07-14T13:50:46Z"
      }
    },
    {
      "description": "recommendation concurred in",
      "date": "2026-02-18",
      "organization_id": "~{\"classification\": \"lower\"}",
      "classification": [],
      "related_entities": [],
      "_processing": {
        "log_file_created": "2026-07-14T13:50:46Z"
      }
    }
  ],
  "sponsorships": [
    {
      "name": "Matt Bierlein",
      "classification": "primary",
      "entity_type": "person",
      "primary": true,
      "person_id": "~{\"name\": \"Matt Bierlein\"}",
      "organization_id": null
    },
    {
      "name": "Douglas Wozniak",
      "classification": "cosponsor",
      "entity_type": "person",
      "primary": false,
      "person_id": "~{\"name\": \"Douglas Wozniak\"}",
      "organization_id": null
    },
    {
      "name": "Matt Maddock",
      "classification": "cosponsor",
      "entity_type": "person",
      "primary": false,
      "person_id": "~{\"name\": \"Matt Maddock\"}",
      "organization_id": null
    },
    {
      "name": "Joseph Aragona",
      "classification": "cosponsor",
      "entity_type": "person",
      "primary": false,
      "person_id": "~{\"name\": \"Joseph Aragona\"}",
      "organization_id": null
    },
    {
      "name": "John Roth",
      "classification": "cosponsor",
      "entity_type": "person",
      "primary": false,
      "person_id": "~{\"name\": \"John Roth\"}",
      "organization_id": null
    },
    {
      "name": "Nancy DeBoer",
      "classification": "cosponsor",
      "entity_type": "person",
      "primary": false,
      "person_id": "~{\"name\": \"Nancy DeBoer\"}",
      "organization_id": null
    },
    {
      "name": "Mike Hoadley",
      "classification": "cosponsor",
      "entity_type": "person",
      "primary": false,
      "person_id": "~{\"name\": \"Mike Hoadley\"}",
      "organization_id": null
    },
    {
      "name": "Ron Robinson",
      "classification": "cosponsor",
      "entity_type": "person",
      "primary": false,
      "person_id": "~{\"name\": \"Ron Robinson\"}",
      "organization_id": null
    },
    {
      "name": "Jason Woolford",
      "classification": "cosponsor",
      "entity_type": "person",
      "primary": false,
      "person_id": "~{\"name\": \"Jason Woolford\"}",
      "organization_id": null
    },
    {
      "name": "Gregory Alexander",
      "classification": "cosponsor",
      "entity_type": "person",
      "primary": false,
      "person_id": "~{\"name\": \"Gregory Alexander\"}",
      "organization_id": null
    },
    {
      "name": "Steve Frisbie",
      "classification": "cosponsor",
      "entity_type": "person",
      "primary": false,
      "person_id": "~{\"name\": \"Steve Frisbie\"}",
      "organization_id": null
    },
    {
      "name": "Timothy Beson",
      "classification": "cosponsor",
      "entity_type": "person",
      "primary": false,
      "person_id": "~{\"name\": \"Timothy Beson\"}",
      "organization_id": null
    },
    {
      "name": "Mark Tisdel",
      "classification": "cosponsor",
      "entity_type": "person",
      "primary": false,
      "person_id": "~{\"name\": \"Mark Tisdel\"}",
      "organization_id": null
    },
    {
      "name": "Cameron Cavitt",
      "classification": "cosponsor",
      "entity_type": "person",
      "primary": false,
      "person_id": "~{\"name\": \"Cameron Cavitt\"}",
      "organization_id": null
    },
    {
      "name": "Luke Meerman",
      "classification": "cosponsor",
      "entity_type": "person",
      "primary": false,
      "person_id": "~{\"name\": \"Luke Meerman\"}",
      "organization_id": null
    }
  ],
  "related_bills": [],
  "versions": [
    {
      "note": "House Introduced Bill",
      "links": [
        {
          "url": "https://legislature.mi.gov/documents/2025-2026/billintroduced/House/pdf/2025-HIB-5313.pdf",
          "media_type": "application/pdf"
        },
        {
          "url": "https://legislature.mi.gov/documents/2025-2026/billintroduced/House/htm/2025-HIB-5313.htm",
          "media_type": "text/html"
        }
      ],
      "date": "",
      "classification": ""
    }
  ],
  "documents": [
    {
      "note": "Summary as Introduced (02/17/2026)",
      "links": [
        {
          "url": "https://legislature.mi.gov/documents/2025-2026/billanalysis/House/pdf/2025-HLA-5313-5Z3LQSTG.pdf",
          "media_type": "application/pdf"
        }
      ],
      "date": "",
      "classification": ""
    }
  ],
  "citations": [],
  "sources": [
    {
      "url": "https://legislature.mi.gov/Bills/Bill?ObjectName=2025-HB-5313",
      "note": ""
    }
  ],
  "extras": {},
  "jurisdiction": {
    "id": "ocd-jurisdiction/country:us/state:mi/government",
    "name": "Michigan",
    "classification": "state",
    "division_id": "ocd-division/country:us/state:mi"
  },
  "_processing": {
    "logs_latest_update": "2026-07-14T13:50:46Z"
  }
}