{
  "legislative_session": "2025-2026",
  "identifier": "HB 5236",
  "title": "Individual income tax: property tax credit; definition of homestead; modify. Amends sec. 508 of 1967 PA 281 (MCL 206.508).",
  "from_organization": "~{\"classification\": \"lower\"}",
  "classification": [
    "bill"
  ],
  "subject": [
    "Individual income tax: property tax credit"
  ],
  "abstracts": [],
  "other_titles": [],
  "other_identifiers": [
    {
      "identifier": "ocd-bill-mi-2025_2026-hb5236"
    }
  ],
  "actions": [
    {
      "description": "introduced by Representative Rep. Bill Schuette",
      "date": "2025-11-06",
      "organization_id": "~{\"classification\": \"lower\"}",
      "classification": [
        "introduction"
      ],
      "related_entities": [],
      "_processing": {
        "log_file_created": "2026-07-13T06:03:10Z"
      }
    },
    {
      "description": "read a first time",
      "date": "2025-11-06",
      "organization_id": "~{\"classification\": \"lower\"}",
      "classification": [
        "reading-1"
      ],
      "related_entities": [],
      "_processing": {
        "log_file_created": "2026-07-13T06:03:10Z"
      }
    },
    {
      "description": "referred to Committee on Judiciary",
      "date": "2025-11-06",
      "organization_id": "~{\"classification\": \"lower\"}",
      "classification": [
        "referral-committee"
      ],
      "related_entities": [],
      "_processing": {
        "log_file_created": "2026-07-13T06:03:10Z"
      }
    },
    {
      "description": "bill electronically reproduced 11/06/2025",
      "date": "2025-11-12",
      "organization_id": "~{\"classification\": \"lower\"}",
      "classification": [],
      "related_entities": [],
      "_processing": {
        "log_file_created": "2026-07-13T06:03:10Z"
      }
    },
    {
      "description": "reported with recommendation for referral to Committee on Finance",
      "date": "2026-05-20",
      "organization_id": "~{\"classification\": \"lower\"}",
      "classification": [
        "committee-passage"
      ],
      "related_entities": [],
      "_processing": {
        "log_file_created": "2026-07-14T13:50:46Z"
      }
    },
    {
      "description": "recommendation concurred in",
      "date": "2026-05-20",
      "organization_id": "~{\"classification\": \"lower\"}",
      "classification": [],
      "related_entities": [],
      "_processing": {
        "log_file_created": "2026-07-14T13:50:46Z"
      }
    },
    {
      "description": "reported with recommendation with substitute (H-1)",
      "date": "2026-06-09",
      "organization_id": "~{\"classification\": \"lower\"}",
      "classification": [
        "committee-passage"
      ],
      "related_entities": [],
      "_processing": {
        "log_file_created": "2026-07-14T13:50:46Z"
      }
    },
    {
      "description": "referred to second reading",
      "date": "2026-06-09",
      "organization_id": "~{\"classification\": \"lower\"}",
      "classification": [],
      "related_entities": [],
      "_processing": {
        "log_file_created": "2026-07-14T13:50:46Z"
      }
    }
  ],
  "sponsorships": [
    {
      "name": "Bill Schuette",
      "classification": "primary",
      "entity_type": "person",
      "primary": true,
      "person_id": "~{\"name\": \"Bill Schuette\"}",
      "organization_id": null
    },
    {
      "name": "Jason Woolford",
      "classification": "cosponsor",
      "entity_type": "person",
      "primary": false,
      "person_id": "~{\"name\": \"Jason Woolford\"}",
      "organization_id": null
    },
    {
      "name": "Ron Robinson",
      "classification": "cosponsor",
      "entity_type": "person",
      "primary": false,
      "person_id": "~{\"name\": \"Ron Robinson\"}",
      "organization_id": null
    }
  ],
  "related_bills": [],
  "versions": [
    {
      "note": "Substitute (H-1)",
      "links": [
        {
          "url": "https://legislature.mi.gov/Home/GetObject?objectName=2025-HCVBH-5236-0N297.pdf",
          "media_type": "application/pdf"
        }
      ],
      "date": "",
      "classification": ""
    },
    {
      "note": "House Introduced Bill",
      "links": [
        {
          "url": "https://legislature.mi.gov/documents/2025-2026/billintroduced/House/pdf/2025-HIB-5236.pdf",
          "media_type": "application/pdf"
        },
        {
          "url": "https://legislature.mi.gov/documents/2025-2026/billintroduced/House/htm/2025-HIB-5236.htm",
          "media_type": "text/html"
        }
      ],
      "date": "",
      "classification": ""
    }
  ],
  "documents": [
    {
      "note": "Summary as Introduced (03/04/2026)",
      "links": [
        {
          "url": "https://legislature.mi.gov/documents/2025-2026/billanalysis/House/pdf/2025-HLA-5235-SDT7Y3RC.pdf",
          "media_type": "application/pdf"
        }
      ],
      "date": "",
      "classification": ""
    }
  ],
  "citations": [
    {
      "publication": "Michigan Compiled Laws",
      "citation": "MCL 206.508",
      "citation_type": "proposed",
      "effective": null,
      "expires": null,
      "url": null
    }
  ],
  "sources": [
    {
      "url": "https://legislature.mi.gov/Bills/Bill?ObjectName=2025-HB-5236",
      "note": ""
    }
  ],
  "extras": {},
  "jurisdiction": {
    "id": "ocd-jurisdiction/country:us/state:mi/government",
    "name": "Michigan",
    "classification": "state",
    "division_id": "ocd-division/country:us/state:mi"
  },
  "_processing": {
    "logs_latest_update": "2026-07-14T13:50:46Z",
    "text_extraction_latest_update": "2026-07-14T21:08:57.718175Z"
  }
}